[
  {
    "text": "我从来无法决定我是痛恨英格兰，还是爱它胜过世界上任何地方。",
    "original": "I never could make up my mind whether I hated England, or loved it more than anywhere else in the world.",
    "source": "劳伦斯书信",
    "context": "尽管劳伦斯后半生一直在国外流亡，他对故乡英格兰的矿区景观却有一种无法割舍的情感。他小说中最惊人的风景描写常常是关于诺丁汉矿区在晨光中的粗砺之美。"
  },
  {
    "text": "我从没见过一只野兽为自己感到可怜。一只小鸟会冻僵从枝头跌落死去，却从未为自己感到可怜。",
    "original": "I never saw a wild thing sorry for itself. A small bird will drop frozen dead from a bough without ever having felt sorry for itself.",
    "source": "《自我怜悯》",
    "context": "劳伦斯以极简的笔触道出了他对生命本能的终极信仰——动物不懂得自怜，它们只是活着和死去。这句话反对人类文明中泛滥的自我怜悯和感伤主义，主张以纯粹的生命力量面对苦难，是劳伦斯身体哲学最精炼的表达。"
  },
  {
    "text": "美利坚灵魂的本质是坚硬、孤独、坚忍，并且是杀手。",
    "original": "The essential American soul is hard, isolate, stoic, and a killer.",
    "source": "《经典美国文学研究》",
    "context": "劳伦斯在评论美国经典文学时对美国精神气质的核心判断。他认为美国文学中表面的自由和民主之下掩藏着一种原始的、暴力的孤独——从库柏的拓荒者到麦尔维尔的亚哈船长，美国灵魂的本质是离开人群独自面对荒野和死亡。"
  },
  {
    "text": "一个人必须学会去爱，要经历许多苦难才能到达爱的境界……这段旅程永远朝着另一个灵魂。",
    "original": "One must learn to love, and go through a good deal of suffering to get to it... and the journey is always towards the other soul.",
    "source": "劳伦斯书信",
    "context": "劳伦斯在写给未婚妻弗里达的信中表达了他对爱的理解。他反对将爱视为本能或浪漫冲动，而将其定义为一个需要通过痛苦和自我否定才能抵达的精神目标。爱的本质不是占有而是走向另一个灵魂的旅程——这正是他全部小说的情感结构。"
  }
]
