[
  {
    "text": "冬天来了，春天还会远吗？",
    "original": "If Winter comes, can Spring be far behind?",
    "source": "《西风颂》结尾",
    "context": "雪莱最著名的一句诗，写在1819年拿破仑战争后欧洲仍在反动势力统治下的时代。这句诗用最少的字将个人对季节变换的观察转化为对人类历史必然走向自由的信念宣言。"
  },
  {
    "text": "诗人是未被承认的世界的立法者。",
    "original": "Poets are the unacknowledged legislators of the world.",
    "source": "《诗辩》结尾",
    "context": "雪莱对诗人社会功能的终极定义。在他笔下，诗人不是美的装饰者而是人类意识的先行塑造者。"
  },
  {
    "text": "看看我的杰作吧，你们这些强者，然后绝望吧！",
    "original": "Look on my Works, ye Mighty, and despair!",
    "source": "《奥兹曼迪亚斯》",
    "context": "雪莱在十四行诗中借古埃及法老拉美西斯二世残破雕像上的铭文，对一切世俗权力的永恒讽刺。曾经不可一世的帝王和他庞大的帝国已化为沙漠中的废墟，唯有诗篇长存。这首诗写于1817年，暗含对英国殖民扩张和一切政治傲慢的警训。"
  },
  {
    "text": "我们最甜美的歌是那些诉说最悲伤思绪的歌。",
    "original": "Our sweetest songs are those that tell of saddest thought.",
    "source": "《致云雀》",
    "context": "雪莱凝听云雀的歌声后写下的诗句。云雀在高空中无拘无束地歌唱，是人类纯粹欢乐的象征，但雪莱敏锐地发现最深的欢乐与最深的悲伤相连——因为对必朽者而言，一切美的体验都包含着对消逝的预感。这是浪漫主义对悲剧意识最精微的表达之一。"
  },
  {
    "text": "我希望我会给予你我的诗，让那诗如火星一般落在人类冰冷的心上。",
    "original": "I would give / My song to thee, as with a spark / It lights up the cold hearth of the human heart.",
    "source": "《致云雀》",
    "context": "雪莱对诗歌力量的终极信念——诗歌不是文字的排列而是精神的火焰，它的使命是点燃被冷漠和绝望冰封的人类心灵。雪莱将诗人比作普罗米修斯式的盗火者，以语言的火花照亮黑暗中的世界。"
  }
]
