[
  {
    "phase": "天主教视野与南方怪诞",
    "period": "1946-1955",
    "description": "奥康纳的核心思想可以用她自己的一句话概括：我之所以这样写，是因为我是天主教徒。但她的天主教不是说教——她拒绝一切将宗教简化为道德训诫的写作。她所理解的信仰是托马斯·阿奎那式的：恩典不是温柔安慰，而是暴力的介入，它打破人的自以为义，在破碎中揭示真理。这一神学立场使她选择了南方哥特的怪诞传统作为文学载体。怪诞不是猎奇，而是一种认知策略：当世俗小说无法触及终极问题时，怪诞可以通过震惊让读者看见日常遮蔽的宗教维度。她笔下的角色——自盲的先知、杀人犯、偏执的种族主义者——都是被神恩以最残酷方式击碎的人。在她的世界里，极端暴力往往是恩典降临的条件。",
    "keywords": ["天主教", "神恩", "南方怪诞", "暴力启示"]
  },
  {
    "phase": "南方社会与种族批判",
    "period": "1955-1964",
    "description": "1950年代后期奥康纳的创作深入南方社会的种族和阶级议题。《上升的一切必将汇聚》等短篇直接处理种族主义——不是通过说教，而是通过南方白人女性的自以为义如何被一个黑人男子的存在击碎。奥康纳对南方新教文化的批判尖锐而精确：她认为南方的真正问题不是缺乏道德，而是道德过剩——人们太确定自己是好人，这种自以为义本身就是最大的罪。她的种族批判与天主教原罪观念融合：没有人是清白的，真正的邪恶往往穿着正义的外衣。这一阶段她对南方方言、社会礼仪和阶级信号的把握达到了小说中罕见的精度——每一个对话、每一个餐桌布置都是社会分析的微观样本。",
    "keywords": ["种族批判", "自以为义", "原罪", "南方社会"]
  }
]
